README.md
pyproject.toml
setup.cfg
setup.py
freediv10Xcellbcs/__init__.py
freediv10Xcellbcs/aligners.py
freediv10Xcellbcs/config.py
freediv10Xcellbcs/constants.py
freediv10Xcellbcs/decode.py
freediv10Xcellbcs/discover.py
freediv10Xcellbcs/main.py
freediv10Xcellbcs/misc.py
freediv10Xcellbcs/plotting.py
freediv10Xcellbcs.egg-info/PKG-INFO
freediv10Xcellbcs.egg-info/SOURCES.txt
freediv10Xcellbcs.egg-info/dependency_links.txt
freediv10Xcellbcs.egg-info/entry_points.txt
freediv10Xcellbcs.egg-info/not-zip-safe
freediv10Xcellbcs.egg-info/requires.txt
freediv10Xcellbcs.egg-info/top_level.txt